{
  "library": [
    {
      "title": "Facebook",
      "description": "12345",
      "id": "4300JDWtT",
      "quantity": 1
    },
    {
      "title": "Direct call",
      "description": "aasdad",
      "id": "1qy-2dBRe",
      "quantity": 2
    },
    {
      "id": "1",
      "title": "Francolinus leucoscepus",
      "description": "Pathological fracture, unsp hand, init encntr for fracture",
      "quantity": 2
    },
    {
      "id": "2",
      "title": "Choloepus hoffmani",
      "description": "Drown due to oth accident to water-skis, subs"
    },
    {
      "id": "3",
      "title": "Dusicyon thous",
      "description": "Anemia in neoplastic disease",
      "quantity": 1
    },
    {
      "id": "4",
      "title": "Columba livia",
      "description": "Toxic effect of glycols, intentional self-harm",
      "quantity": 2
    },
    {
      "id": "5",
      "title": "Agkistrodon piscivorus",
      "description": "Cystic meniscus, posterior horn of medial meniscus, r knee"
    },
    {
      "id": "6",
      "title": "Capra ibex",
      "description": "Injury of unspecified blood vessel at forearm level",
      "quantity": 2
    },
    {
      "id": "7",
      "title": "Eubalaena australis",
      "description": "Crohn's disease, unspecified",
      "quantity": 2
    },
    {
      "id": "8",
      "title": "Agelaius phoeniceus",
      "description": "Combined forms of age-related cataract, left eye"
    },
    {
      "id": "9",
      "title": "Nesomimus trifasciatus",
      "description": "Unsp injury of ulnar artery at forarm lv, right arm, init",
      "quantity": 1
    },
    {
      "id": "10",
      "title": "Thalasseus maximus",
      "description": "Nondisp pilon fx r tibia, 7thE"
    },
    {
      "id": "11",
      "title": "Loxodonta africana",
      "description": "Anomalous implantation of ureter"
    },
    {
      "id": "12",
      "title": "unavailable",
      "description": "War op involving explosion of unsp marine weapon, milt, subs"
    },
    {
      "id": "13",
      "title": "Trichosurus vulpecula",
      "description": "Sltr-haris Type I physeal fx upper end of left tibia"
    },
    {
      "id": "14",
      "title": "Melanerpes erythrocephalus",
      "description": "Laceration w/o fb of finger w/o damage to nail, sequela"
    },
    {
      "id": "15",
      "title": "Tyto novaehollandiae",
      "description": "Displ pilon fx l tibia, subs for opn fx type I/2 w malunion"
    },
    {
      "id": "16",
      "title": "Canis lupus baileyi",
      "description": "Wedge comprsn fx T5-T6 vertebra, subs for fx w routn heal"
    },
    {
      "id": "17",
      "title": "Mephitis mephitis",
      "description": "Car driver injured in collision w van nontraf, init"
    },
    {
      "id": "18",
      "title": "Neotis denhami",
      "description": "Abrasion of left forearm, sequela"
    },
    {
      "id": "19",
      "title": "Myiarchus tuberculifer",
      "description": "Supervision of young primigravida, third trimester"
    },
    {
      "id": "20",
      "title": "Buteo jamaicensis",
      "description": "Other fracture of unsp ilium, init encntr for open fracture"
    },
    {
      "id": "21",
      "title": "Crotalus triseriatus",
      "description": "Drown due to oth accident to canoe or kayak, subs"
    },
    {
      "id": "22",
      "title": "Hystrix cristata",
      "description": "Other congenital malformations of nervous system"
    },
    {
      "id": "23",
      "title": "Felis concolor",
      "description": "Tinea imbricata"
    },
    {
      "id": "24",
      "title": "Vulpes vulpes",
      "description": "Mechanical entropion of left eye, unspecified eyelid"
    },
    {
      "id": "25",
      "title": "Taxidea taxus",
      "description": "Sltr-haris Type II physeal fx lower end of left fibula, init"
    },
    {
      "id": "26",
      "title": "Tamandua tetradactyla",
      "description": "Milt op involving unsp dest arcrft, milt, sequela"
    },
    {
      "id": "27",
      "title": "Lybius torquatus",
      "description": "Cerebral cysts"
    },
    {
      "id": "28",
      "title": "Felis silvestris lybica",
      "description": "Polyarthritis, unspecified"
    },
    {
      "id": "29",
      "title": "Ramphastos tucanus",
      "description": "Hemarthrosis, unspecified wrist"
    },
    {
      "id": "30",
      "title": "Galictis vittata",
      "description": "Secondary malignant neoplasm of cerebral meninges"
    },
    {
      "id": "31",
      "title": "Larus dominicanus",
      "description": "Other superficial bite of unspecified lesser toe(s), sequela"
    },
    {
      "id": "32",
      "title": "Tachyglossus aculeatus",
      "description": "Displaced pilon fracture of left tibia, sequela"
    },
    {
      "id": "33",
      "title": "Felis concolor",
      "description": "Toxic effect of rodenticides, accidental, subs"
    },
    {
      "id": "34",
      "title": "Macropus eugenii",
      "description": "Adverse effect of tetracyclines, subsequent encounter"
    },
    {
      "id": "35",
      "title": "Stenella coeruleoalba",
      "description": "Open wound of ankle"
    },
    {
      "id": "36",
      "title": "Varanus salvator",
      "description": "Intestinal strongyloidiasis"
    },
    {
      "id": "37",
      "title": "Macropus eugenii",
      "description": "Nondisp fx of lateral condyle of r tibia, 7thC"
    },
    {
      "id": "38",
      "title": "Phalacrocorax niger",
      "description": "Leakage of internal prosth dev/grft, subs"
    },
    {
      "id": "39",
      "title": "Estrilda erythronotos",
      "description": "Other benign neoplasm of skin of scalp and neck"
    },
    {
      "id": "40",
      "title": "Otaria flavescens",
      "description": "Toxic effect of chlorine gas"
    },
    {
      "id": "41",
      "title": "Grus antigone",
      "description": "Other juvenile arthritis, multiple sites"
    },
    {
      "id": "42",
      "title": "Antilocapra americana",
      "description": "Nondisp fx of less tuberosity of unsp humer, 7thG"
    },
    {
      "id": "43",
      "title": "Pseudocheirus peregrinus",
      "description": "Kissing spine, thoracolumbar region"
    },
    {
      "id": "44",
      "title": "Cebus apella",
      "description": "Lacerat unsp musc/fasc/tend at wrs/hnd lv, l hand, sequela"
    },
    {
      "id": "45",
      "title": "Crotalus adamanteus",
      "description": "Poisoning by anterior pituitary hormones, assault, init"
    },
    {
      "id": "46",
      "title": "Calyptorhynchus magnificus",
      "description": "Major depressive disorder, recurrent, moderate"
    },
    {
      "id": "47",
      "title": "Nannopterum harrisi",
      "description": "Age-rel osteopor w crnt path fx, r humer, 7thG"
    },
    {
      "id": "48",
      "title": "Zenaida galapagoensis",
      "description": "Assault by hot tap water, initial encounter"
    },
    {
      "id": "49",
      "title": "Egretta thula",
      "description": "Other adult osteomalacia"
    },
    {
      "id": "50",
      "title": "Manouria emys",
      "description": "Inferior dislocation of left humerus"
    },
    {
      "id": "51",
      "title": "Ratufa indica",
      "description": "Toxic effect of rattlesnake venom, self-harm, sequela"
    },
    {
      "id": "52",
      "title": "Gazella thompsonii",
      "description": "I/I react d/t other prosth dev/grft in genital tract, subs"
    },
    {
      "id": "53",
      "title": "Thylogale stigmatica",
      "description": "Thrombosis due to internal orth prosth dev/grft, sequela"
    },
    {
      "id": "54",
      "title": "Tiliqua scincoides",
      "description": "Athscl heart disease of native cor art w ang pctrs w spasm"
    },
    {
      "id": "55",
      "title": "Propithecus verreauxi",
      "description": "Oth physl fx lower end of unsp femur, subs for fx w nonunion"
    },
    {
      "id": "56",
      "title": "Macaca mulatta",
      "description": "Oth nondisp fx of base of 1st MC bone, l hand, 7thP"
    },
    {
      "id": "57",
      "title": "Chauna torquata",
      "description": "Puncture wound w foreign body of oth finger w damage to nail"
    },
    {
      "id": "58",
      "title": "Tragelaphus scriptus",
      "description": "Unsp inj unsp musc/fasc/tend at thi lev, right thigh, sqla"
    },
    {
      "id": "59",
      "title": "Lamprotornis chalybaeus",
      "description": "Person outsd 3-whl mv inj in clsn w nonmtr veh nontraf, init"
    },
    {
      "id": "60",
      "title": "Vulpes chama",
      "description": "Path fx in neopltc disease, oth site, subs for fx w malunion"
    },
    {
      "id": "61",
      "title": "Graspus graspus",
      "description": "Unspecified open wound of unspecified elbow, subs encntr"
    },
    {
      "id": "62",
      "title": "Spermophilus richardsonii",
      "description": "Infantile acne"
    },
    {
      "id": "63",
      "title": "Dicrurus adsimilis",
      "description": "Nondisp fx of 1st metatarsal bone, r ft, 7thK"
    },
    {
      "id": "64",
      "title": "Nyctereutes procyonoides",
      "description": "Breakdown (mechanical) of implnt elec nstim, generator"
    },
    {
      "id": "65",
      "title": "Cebus apella",
      "description": "Fall from or off toilet w/o strike against object, init"
    },
    {
      "id": "66",
      "title": "Haematopus ater",
      "description": "Sprain of interphalangeal joint of left lesser toe(s)"
    },
    {
      "id": "67",
      "title": "Aonyx cinerea",
      "description": "Post-traumatic urethral stricture, female"
    },
    {
      "id": "68",
      "title": "Ceryle rudis",
      "description": "Inj left quadriceps muscle, fascia and tendon, init encntr"
    },
    {
      "id": "69",
      "title": "Ara chloroptera",
      "description": "Unsp pedl cyclst inj in clsn w statnry object nontraf, sqla"
    },
    {
      "id": "70",
      "title": "Anitibyx armatus",
      "description": "Abnormal microbiological findings in cerebrospinal fluid"
    },
    {
      "id": "71",
      "title": "Tamiasciurus hudsonicus",
      "description": "Person inj wh brd/alit from special industr vehicle, init"
    },
    {
      "id": "72",
      "title": "Phoenicopterus ruber",
      "description": "Goniosynechiae, left eye"
    },
    {
      "id": "73",
      "title": "Vanellus armatus",
      "description": "Oth soft tissue disord related to use/pressure, right ank/ft"
    },
    {
      "id": "74",
      "title": "Corvus albicollis",
      "description": "Superficial foreign body of right shoulder, init encntr"
    },
    {
      "id": "75",
      "title": "Tiliqua scincoides",
      "description": "Early syphilis, latent"
    },
    {
      "id": "76",
      "title": "Vulpes chama",
      "description": "Matern care for disproprtn d/t unusually large fetus, fts2"
    },
    {
      "id": "77",
      "title": "Canis lupus lycaon",
      "description": "Glaucoma secondary to drugs, bilateral"
    },
    {
      "id": "78",
      "title": "Gymnorhina tibicen",
      "description": "Chronic lymphocytic leukemia of B-cell type in relapse"
    },
    {
      "id": "79",
      "title": "Kobus defassa",
      "description": "Animal-rider injured in collision w anml-drn vehicle, subs"
    },
    {
      "id": "80",
      "title": "Snycerus caffer",
      "description": "Other congenital malformations of aortic and mitral valves"
    },
    {
      "id": "81",
      "title": "Acrobates pygmaeus",
      "description": "Hemarthrosis, right ankle"
    },
    {
      "id": "82",
      "title": "Gekko gecko",
      "description": "Unspecified physeal fracture of left calcaneus, init"
    },
    {
      "id": "83",
      "title": "Castor canadensis",
      "description": "Fracture of body of sternum, init encntr for closed fracture"
    },
    {
      "id": "84",
      "title": "Macropus parryi",
      "description": "Inj extensor musc/fasc/tend r idx fngr at wrs/hnd lv, init"
    },
    {
      "id": "85",
      "title": "Phalacrocorax brasilianus",
      "description": "Pathological fracture, left hand, subs for fx w routn heal"
    },
    {
      "id": "86",
      "title": "Francolinus coqui",
      "description": "Complete traumatic amputation of unsp midfoot, subs encntr"
    },
    {
      "id": "87",
      "title": "Stenella coeruleoalba",
      "description": "Passenger in hv veh injured in clsn w ped/anml nontraf, init"
    },
    {
      "id": "88",
      "title": "Grus canadensis",
      "description": "Acute on chronic slipped upper femoral epiphysis, left hip"
    },
    {
      "id": "89",
      "title": "Dendrohyrax brucel",
      "description": "Sltr-haris Type I physl fx upper end humer, left arm, sqla"
    },
    {
      "id": "90",
      "title": "Sylvilagus floridanus",
      "description": "Anterior cord syndrome at C5 level of cervical spinal cord"
    },
    {
      "id": "91",
      "title": "Cervus canadensis",
      "description": "Displ osteochon fx l patella, 7thF"
    },
    {
      "id": "92",
      "title": "Dicrurus adsimilis",
      "description": "Retained (old) fb in posterior wall of globe, left eye"
    },
    {
      "id": "93",
      "title": "Canis mesomelas",
      "description": "Burn of first degree of right shoulder"
    },
    {
      "id": "94",
      "title": "Chordeiles minor",
      "description": "Hemorrhage from other sites in respiratory passages"
    },
    {
      "id": "95",
      "title": "Crotalus cerastes",
      "description": "Other specified injuries of left elbow, initial encounter"
    },
    {
      "id": "96",
      "title": "Ammospermophilus nelsoni",
      "description": "Laceration of dorsal vein of right foot, subs encntr"
    },
    {
      "id": "97",
      "title": "Macropus eugenii",
      "description": "Oth degeneratv disord of nervous sys in dis classd elswhr"
    },
    {
      "id": "98",
      "title": "Thalasseus maximus",
      "description": "Bennett's fracture, unsp hand, init for clos fx"
    },
    {
      "id": "99",
      "title": "Platalea leucordia",
      "description": "Displ commnt fx shaft of l tibia, 7thG"
    },
    {
      "id": "100",
      "title": "Phalaropus lobatus",
      "description": "Unsp focal TBI w LOC of 30 minutes or less, sequela"
    }
  ],
  "users": [
    {
      "isAdmin": true,
      "id": "UwWPPRDCD",
      "emailLogin": "huynt.seo@gmail.com",
      "passLogin": "$2b$10$dsjG1nHwg5Sp8gQLKTr02etXl/SLr/WrRAeqFUKAIZqEhIxyRPYP6",
      "name": "Nguyễn Tuấn Huy",
      "introduce": "Xin chào tôi là Huy",
      "checkLogin": 0,
      "avatar": "uploads/d461318ca9c2216f31be7a3cf352dd0d"
    },
    {
      "isAdmin": false,
      "id": "UwWPPRasDD",
      "emailLogin": "huy@gmail.com",
      "passLogin": "$2b$10$dsjG1nHwg5Sp8gQLKTr02etXl/SLr/WrRAeqFUKAIZqEhIxyRPYP6",
      "name": "Nguyễn Tuấn Huy",
      "introduce": "Xin chào tôi là Huy",
      "checkLogin": 0,
      "avatar": "uploads/d461318ca9c2216f31be7a3cf352dd0d"
    },
    {
      "isAdmin": false,
      "id": "Uasdcgq3D",
      "emailLogin": "huynt@gmail.com",
      "passLogin": "$2b$10$dsjG1nHwg5Sp8gQLKTr02etXl/SLr/WrRAeqFUKAIZqEhIxyRPYP6",
      "name": "Nguyễn Tuấn Huy",
      "introduce": "Xin chào tôi là Huy",
      "checkLogin": 0,
      "avatar": "uploads/d461318ca9c2216f31be7a3cf352dd0d"
    }
  ],
  "transactions": [
    {
      "id": "TM-dNZfn-h",
      "isComplete": false,
      "user": {
        "userId": "Uasdcgq3D"
      },
      "book": {
        "bookId": "3"
      }
    },
    {
      "id": "cdxlrcOjp",
      "isComplete": false,
      "user": {
        "userId": "UwWPPRDCD"
      },
      "book": {
        "bookId": "3"
      }
    },
    {
      "id": "McURU_iC4",
      "isComplete": false,
      "user": {
        "userId": "UwWPPRDCD"
      },
      "book": {
        "bookId": "3"
      }
    },
    {
      "id": "rV6_h88bPg",
      "isComplete": false,
      "user": {
        "userId": "UwWPPRDCD"
      },
      "book": {
        "bookId": "4"
      }
    },
    {
      "id": "XfKP3qgUmP",
      "isComplete": false,
      "user": {
        "userId": "UwWPPRDCD"
      },
      "book": {
        "bookId": "4"
      }
    },
    {
      "id": "OGTdgYSYI",
      "isComplete": false,
      "user": {
        "userId": "UwWPPRDCD"
      },
      "book": {
        "bookId": "1qy-2dBRe"
      }
    },
    {
      "id": "fygjJt-oGi",
      "isComplete": false,
      "user": {
        "userId": "UwWPPRDCD"
      },
      "book": {
        "bookId": "1qy-2dBRe"
      }
    },
    {
      "id": "r4E25b1DP",
      "isComplete": false,
      "user": {
        "userId": "UwWPPRDCD"
      },
      "book": {
        "bookId": "9"
      }
    },
    {
      "id": "lZQymKuIDP",
      "isComplete": false,
      "user": {
        "userId": "UwWPPRDCD"
      },
      "book": {
        "bookId": "4300JDWtT"
      }
    }
  ],
  "sessions": [
    {
      "id": "kjuL8ED8e"
    },
    {
      "id": "xlN9nmOgSV"
    },
    {
      "id": "kGR2csf0e2"
    },
    {
      "id": "5kPuWb5f5",
      "cart": {
        "1": 2,
        "3": 2,
        "4": 1,
        "6": 1,
        "4300JDWtT": 2,
        "1qy-2dBRe": 5
      }
    },
    {
      "id": "LN8dd4Rdc"
    },
    {
      "id": "yk7zXxJv-",
      "cart": {
        "1qy-2dBRe": 1,
        "4300JDWtT": 1
      }
    },
    {
      "id": "qbdoQHCOy",
      "cart": {
        "34": 1,
        "1qy-2dBRe": 2,
        "4300JDWtT": 2
      }
    },
    {
      "id": "wP7U1JG9I"
    },
    {
      "id": "pyU9IOCn5"
    },
    {
      "id": "yL_rvUA63",
      "cart": {
        "4300JDWtT": 3,
        "1qy-2dBRe": 1
      }
    },
    {
      "id": "k_UQ83o9C"
    },
    {
      "id": "zbE_Nht34",
      "cart": [
        null,
        null,
        null,
        1,
        2
      ]
    },
    {
      "id": "d1iTGtqG_",
      "cart": [
        null,
        null,
        null,
        1
      ]
    },
    {
      "id": "HGf-sn1fO"
    },
    {
      "id": "LT9JCxpuS"
    },
    {
      "id": "-ngfLYSyJ",
      "cart": {
        "1qy-2dBRe": 2
      }
    },
    {
      "id": "HoSq4wH6E",
      "cart": {
        "9": 1,
        "4300JDWtT": 1
      }
    }
  ]
}